LICENSE.md
MANIFEST.in
README.md
setup.py
admin_material/__init__.py
admin_material/admin.py
admin_material/apps.py
admin_material/forms.py
admin_material/models.py
admin_material/tests.py
admin_material/urls.py
admin_material/utils.py
admin_material/views.py
admin_material/static/.gitkeep
admin_material/static/assets/css/forms.css
admin_material/static/assets/css/material-dashboard.css
admin_material/static/assets/css/material-dashboard.css.map
admin_material/static/assets/css/material-dashboard.min.css
admin_material/static/assets/css/nucleo-icons.css
admin_material/static/assets/css/nucleo-svg.css
admin_material/static/assets/css/widgets.css
admin_material/static/assets/fonts/nucleo-icons.eot
admin_material/static/assets/fonts/nucleo-icons.svg
admin_material/static/assets/fonts/nucleo-icons.ttf
admin_material/static/assets/fonts/nucleo-icons.woff
admin_material/static/assets/fonts/nucleo-icons.woff2
admin_material/static/assets/fonts/nucleo.eot
admin_material/static/assets/fonts/nucleo.ttf
admin_material/static/assets/fonts/nucleo.woff
admin_material/static/assets/fonts/nucleo.woff2
admin_material/static/assets/images/icon-calendar.svg
admin_material/static/assets/images/icon-clock.svg
admin_material/static/assets/images/icon-unknown-alt.svg
admin_material/static/assets/images/icon-unknown.svg
admin_material/static/assets/images/search.svg
admin_material/static/assets/images/selector-icons.svg
admin_material/static/assets/img/apple-icon.png
admin_material/static/assets/img/avatar.jpg
admin_material/static/assets/img/bg-pricing.jpg
admin_material/static/assets/img/bg-smart-home-1.jpg
admin_material/static/assets/img/bg-smart-home-2.jpg
admin_material/static/assets/img/bruce-mars.jpg
admin_material/static/assets/img/csv.png
admin_material/static/assets/img/down-arrow-dark.svg
admin_material/static/assets/img/down-arrow-white.svg
admin_material/static/assets/img/down-arrow.svg
admin_material/static/assets/img/drake.jpg
admin_material/static/assets/img/export.png
django_admin_material_dashboard.egg-info/PKG-INFO
django_admin_material_dashboard.egg-info/SOURCES.txt
django_admin_material_dashboard.egg-info/dependency_links.txt
django_admin_material_dashboard.egg-info/not-zip-safe
django_admin_material_dashboard.egg-info/top_level.txt
